urduhack/__init__.py
urduhack/about.py
urduhack/config.py
urduhack/stop_words.py
urduhack/urdu_characters.py
urduhack/command/__init__.py
urduhack/command/cli.py
urduhack/command/cmd_download.py
urduhack/command/cmd_info.py
urduhack/conll/__init__.py
urduhack/conll/conllable.py
urduhack/conll/parser.py
urduhack/conll/reader.py
urduhack/conll/tests/__init__.py
urduhack/conll/tests/test_parser.py
urduhack/conll/tests/test_reader.py
urduhack/core/__init__.py
urduhack/core/unit/__init__.py
urduhack/core/unit/document.py
urduhack/core/unit/sentence.py
urduhack/core/unit/token.py
urduhack/core/unit/tests/__init__.py
urduhack/core/unit/tests/test_document.py
urduhack/core/unit/tests/test_sentence.py
urduhack/core/unit/tests/test_token.py
urduhack/datasets/__init__.py
urduhack/datasets/image/__init__.py
urduhack/datasets/image/hand_written.py
urduhack/datasets/text/__init__.py
urduhack/datasets/text/imdb_urdu.py
urduhack/models/__init__.py
urduhack/models/common/__init__.py
urduhack/models/common/vocab.py
urduhack/models/common/tests/__init__.py
urduhack/models/common/tests/test_vocab.py
urduhack/models/lemmatizer/__init__.py
urduhack/models/lemmatizer/lemmatizer.py
urduhack/models/ner/__init__.py
urduhack/models/ner/model.py
urduhack/models/ner/predict.py
urduhack/models/pos_tagger/__init__.py
urduhack/models/pos_tagger/model.py
urduhack/models/pos_tagger/predict.py
urduhack/normalization/__init__.py
urduhack/normalization/character.py
urduhack/normalization/regexes.py
urduhack/normalization/tests/__init__.py
urduhack/normalization/tests/test_character.py
urduhack/pipeline/__init__.py
urduhack/pipeline/core.py
urduhack/pipeline/parser.py
urduhack/pipeline/parsers/__init__.py
urduhack/pipeline/parsers/lemma.py
urduhack/pipeline/parsers/ner.py
urduhack/pipeline/parsers/normalize.py
urduhack/pipeline/parsers/pos_tagger.py
urduhack/pipeline/parsers/tokenize.py
urduhack/preprocessing/__init__.py
urduhack/preprocessing/character.py
urduhack/preprocessing/regexes.py
urduhack-1.1.1.dist-info/LICENSE
urduhack-1.1.1.dist-info/METADATA
urduhack-1.1.1.dist-info/WHEEL
urduhack-1.1.1.dist-info/entry_points.txt
urduhack-1.1.1.dist-info/top_level.txt
urduhack-1.1.1.dist-info/RECORD
