Metadata-Version: 2.1
Name: urduhack
Version: 1.1.1
Summary: Natural Language Processing (NLP) library for Urdu language.
Home-page: https://github.com/urduhack/urduhack
Author: Ikram Ali
Author-email: mrikram1989@gmail.com
License: MIT License
Project-URL: Documentation, https://urduhack.readthedocs.io/en/stable/
Project-URL: Source, https://github.com/urduhack/urduhack
Project-URL: Bug Tracker, https://github.com/urduhack/urduhack/issues
Keywords: urdu machine learning text pre-processing tensorflow nlp
Platform: UNKNOWN
Classifier: Development Status :: 4 - Beta
Classifier: Intended Audience :: Developers
Classifier: Intended Audience :: Education
Classifier: Intended Audience :: Science/Research
Classifier: License :: OSI Approved :: MIT License
Classifier: Operating System :: POSIX :: Linux
Classifier: Operating System :: MacOS :: MacOS X
Classifier: Operating System :: Microsoft :: Windows
Classifier: Programming Language :: Python :: 3
Classifier: Programming Language :: Python :: 3.6
Classifier: Programming Language :: Python :: 3.7
Classifier: Programming Language :: Python :: 3.8
Classifier: Topic :: Software Development :: Libraries
Classifier: Topic :: Software Development :: Libraries :: Python Modules
Classifier: Natural Language :: Urdu
Classifier: Topic :: Text Processing :: Linguistic
Requires-Python: >= 3.6
Requires-Dist: tf2crf
Requires-Dist: tensorflow-datasets (~=3.1)
Requires-Dist: Click (~=7.1)
Requires-Dist: regex
Provides-Extra: tf
Requires-Dist: tensorflow (~=2.2) ; extra == 'tf'
Provides-Extra: tf-gpu
Requires-Dist: tensorflow-gpu (~=2.2) ; extra == 'tf-gpu'
